odoo/addons/maintenance_equipment_certification/README.rst
odoo/addons/maintenance_equipment_certification/__init__.py
odoo/addons/maintenance_equipment_certification/__manifest__.py
odoo/addons/maintenance_equipment_certification/i18n/es.po
odoo/addons/maintenance_equipment_certification/i18n/it.po
odoo/addons/maintenance_equipment_certification/i18n/maintenance_equipment_certification.pot
odoo/addons/maintenance_equipment_certification/models/__init__.py
odoo/addons/maintenance_equipment_certification/models/maintenance_equipment.py
odoo/addons/maintenance_equipment_certification/models/maintenance_equipment_certificate.py
odoo/addons/maintenance_equipment_certification/readme/CONTRIBUTORS.rst
odoo/addons/maintenance_equipment_certification/readme/DESCRIPTION.rst
odoo/addons/maintenance_equipment_certification/readme/USAGE.rst
odoo/addons/maintenance_equipment_certification/security/ir.model.access.csv
odoo/addons/maintenance_equipment_certification/static/description/icon.png
odoo/addons/maintenance_equipment_certification/static/description/index.html
odoo/addons/maintenance_equipment_certification/tests/__init__.py
odoo/addons/maintenance_equipment_certification/tests/test_maintenance_equipment_certification.py
odoo/addons/maintenance_equipment_certification/views/maintenance_equipment_views.xml
odoo_addon_maintenance_equipment_certification-16.0.1.0.0.4.dist-info/METADATA
odoo_addon_maintenance_equipment_certification-16.0.1.0.0.4.dist-info/WHEEL
odoo_addon_maintenance_equipment_certification-16.0.1.0.0.4.dist-info/top_level.txt
odoo_addon_maintenance_equipment_certification-16.0.1.0.0.4.dist-info/RECORD
